deep_research/__init__.py
deep_research/server.py
deep_research_mcp_server-0.1.0.dist-info/licenses/LICENSE
deep_research_mcp_server-0.1.0.dist-info/METADATA
deep_research_mcp_server-0.1.0.dist-info/WHEEL
deep_research_mcp_server-0.1.0.dist-info/entry_points.txt
deep_research_mcp_server-0.1.0.dist-info/top_level.txt
deep_research_mcp_server-0.1.0.dist-info/RECORD
