Metadata-Version: 2.4
Name: deep-research-mcp-server
Version: 0.1.0
Summary: A MCP server for deep research and report generation
Author-email: Xing Xing <xing@readingplus.ai>
Requires-Python: >=3.13
License-File: LICENSE
Requires-Dist: asyncio>=3.4.3
Requires-Dist: mcp>=1.6.0
Dynamic: license-file
